llama_index/readers/youtube_transcript/__init__.py
llama_index/readers/youtube_transcript/base.py
llama_index/readers/youtube_transcript/utils.py
llama_index_readers_youtube_transcript-0.4.1.dist-info/METADATA
llama_index_readers_youtube_transcript-0.4.1.dist-info/WHEEL
llama_index_readers_youtube_transcript-0.4.1.dist-info/licenses/LICENSE
llama_index_readers_youtube_transcript-0.4.1.dist-info/RECORD
