Metadata-Version: 2.4
Name: llama-index-readers-youtube-transcript
Version: 0.4.1
Summary: llama-index readers youtube transcript integration
Author-email: Your Name <you@example.com>
Maintainer: ravi03071991
License-Expression: MIT
License-File: LICENSE
Keywords: video
Requires-Python: <4.0,>=3.9
Requires-Dist: llama-index-core<0.15,>=0.13.0
Requires-Dist: youtube-transcript-api>=0.5.0
